{
  "type": "matching",
  "introText": "French_Sixth. Prepare “degree five” and go!",
  "keySignature": "#",
  "key": "iE_",
  "chord": [
    {"visible":[59,71],"hidden":[],"rhythmValue":"w"},
    {"visible":[59,67,71,76],"hidden":[],"rhythmValue":"w"},
    {"visible":[60,66,70,76],"hidden":[],"rhythmValue":"w"},
    {"visible":[59,66,71,75],"hidden":[],"rhythmValue":"w"}
  ],
  "reviewText": "",
  "staffDistribution": "keyboard",
  "analysis": {
    "enabled": true,
    "mode": {
      "note_names": false,
      "scientific_pitch": false,
      "scale_degrees": true,
      "solfege": false,
      "roman_numerals": true,
      "intervals": false
    }
  },
  "highlight": {
    "enabled": true,
    "mode": {
      "roothighlight": false,
      "tritonehighlight": false
    }
  }
}
